yaml_resume_builder/__init__.py
yaml_resume_builder/builder.py
yaml_resume_builder/cli.py
yaml_resume_builder/resume.tex.template
yaml_resume_builder/sample_resume.yml
yaml_resume_builder/template_renderer.py
yaml_resume_builder-1.1.2.dist-info/licenses/LICENSE
yaml_resume_builder-1.1.2.dist-info/METADATA
yaml_resume_builder-1.1.2.dist-info/WHEEL
yaml_resume_builder-1.1.2.dist-info/entry_points.txt
yaml_resume_builder-1.1.2.dist-info/top_level.txt
yaml_resume_builder-1.1.2.dist-info/RECORD
