Metadata-Version: 2.4
Name: yaml-resume-builder
Version: 1.1.2
Summary: A package to generate PDF resumes from YAML files using LaTeX templates
Requires-Python: >=3.8
License-File: LICENSE
Requires-Dist: click>=7.1.2
Requires-Dist: jinja2>=3.0.0
Requires-Dist: pyyaml>=5.1
Requires-Dist: pypdf>=4.0.0
Provides-Extra: dev
Requires-Dist: pytest>=8.3.5; extra == "dev"
Requires-Dist: pytest-cov>=4.1.0; extra == "dev"
Requires-Dist: ruff>=0.3.0; extra == "dev"
Requires-Dist: isort>=5.12.0; extra == "dev"
Requires-Dist: black>=24.1.0; extra == "dev"
Requires-Dist: mypy>=1.8.0; extra == "dev"
Requires-Dist: types-PyYAML>=6.0.0; extra == "dev"
Requires-Dist: pytest-mypy-plugins>=3.0.0; extra == "dev"
Requires-Dist: bandit>=1.7.6; extra == "dev"
Requires-Dist: safety>=2.3.5; extra == "dev"
Requires-Dist: pre-commit>=3.5.0; extra == "dev"
Dynamic: license-file
